esplot.py
beaker_es_plot-0.0.0.dist-info/top_level.txt
beaker_es_plot-0.0.0.dist-info/METADATA
beaker_es_plot-0.0.0.dist-info/DESCRIPTION.rst
beaker_es_plot-0.0.0.dist-info/metadata.json
beaker_es_plot-0.0.0.dist-info/WHEEL
beaker_es_plot-0.0.0.dist-info/RECORD
