Metadata-Version: 2.0
Name: beaker-es-plot
Version: 0.0.0
Summary: ESPlot class for Beaker Notebook
Home-page: https://github.com/ei-grad/beaker-es-plot
Author: Andrew Grigorev
Author-email: andrew@ei-grad.ru
License: UNKNOWN
Keywords: elasticsearch beaker beakernotebook plots
Platform: UNKNOWN
Classifier: Development Status :: 3 - Alpha
Classifier: Intended Audience :: Developers
Classifier: Topic :: Internet :: Log Analysis
Classifier: Topic :: Scientific/Engineering :: Information Analysis
Classifier: License :: OSI Approved :: MIT License
Classifier: Programming Language :: Python :: 2
Classifier: Programming Language :: Python :: 2.6
Classifier: Programming Language :: Python :: 2.7
Classifier: Programming Language :: Python :: 3
Classifier: Programming Language :: Python :: 3.2
Classifier: Programming Language :: Python :: 3.3
Classifier: Programming Language :: Python :: 3.4
Requires-Dist: matplotlib
Requires-Dist: python-dateutil
